example/__init__.py
quanpy/__init__.py
quanpy-0.0.5.dist-info/DESCRIPTION.rst
quanpy-0.0.5.dist-info/METADATA
quanpy-0.0.5.dist-info/RECORD
quanpy-0.0.5.dist-info/WHEEL
quanpy-0.0.5.dist-info/metadata.json
quanpy-0.0.5.dist-info/top_level.txt
