Metadata-Version: 2.0
Name: quanpy
Version: 0.0.5
Summary: Quantum Annealing Algorithm Library
Home-page: https://github.com/ymurata/quanpy
Author: ymurata
Author-email: m.yuma0531@gmail.com
License: Apach 2.0
Keywords: quantum annealing
Platform: UNKNOWN
Classifier: Development Status :: 1 - Planning
Classifier: Programming Language :: Python :: 3
